MANIFEST.in
README.rst
setup.py
ipgettercarlos/__init__.py
ipgettercarlos.egg-info/PKG-INFO
ipgettercarlos.egg-info/SOURCES.txt
ipgettercarlos.egg-info/dependency_links.txt
ipgettercarlos.egg-info/not-zip-safe
ipgettercarlos.egg-info/top_level.txt