Metadata-Version: 1.1
Name: ipgettercarlos
Version: 0.1
Summary: a copy of ipgetter made by phoemur which basically does what the name says but improved to work
Home-page: UNKNOWN
Author: The Tempest
Author-email: theterampest@gmail.com
License: MIT
Keywords: ip getter tpain hiphop drake my anaconda dont want none
Platform: UNKNOWN
Classifier: Development Status :: 3 - Alpha
Classifier: License :: OSI Approved :: MIT License
Classifier: Programming Language :: Python :: 2.7
